{
    "meta": {
        "portal_name": "mac-pro",
        "language": "es",
        "updated": "20150502"
    },
    "schema": {
        "html:portal": "http://es.recuweb.com/mac-pro/",
        "graph:videos": "http://es.recuweb.com/graph/v1.0/mac-pro/mac-pro/videos.json",
        "graph:news": "http://es.recuweb.com/graph/v1.0/mac-pro/mac-pro/noticias.json",
        "graph:blogs": "http://es.recuweb.com/graph/v1.0/mac-pro/mac-pro/blogs.json"
    },
    "items": {
        "enewspaper.mx/2015/04/protectores-de-piel-para-macbook-pro-enewspaper": {
            "title": "Protectores de piel para Macbook Pro ENEWSPAPER...",
            "snippet": "Posted on abr 27, 2015. Quienes usan alguna laptop Macbook Pro saben que puede ser \u00fatil tener un protector, adem\u00e1s del car\u00e1cter utilitario los protectores o car\u00e1tulas te ofrecen la posibilidad de cambiarle el look a tu Mac. caratulapiel01.",
            "date": "2015-04-27",
            "author_name": "ENEWSPAPER",
            "categories": "macbook",
            "tags": "adem\u00e1s,puede,macbook,macbook_pro,pro,mac",
            "recuweb_url": "http://es.recuweb.com/macbook/enewspaper.mx/2015/04/protectores-de-piel-para-macbook-pro-enewspaper",
            "resource_url": "http://www.google.com/search?q=mac%2Bpro&tbm=blg&output=atom&start=0&hl=es&lr=lang_es&nord=1",
            "source_url": "http://enewspaper.mx/protectores-de-piel-para-macbook-pro/"
        },
        "applesfera.com/2015/04/nuevo-macbook-el-rendimiento-de-su-cpu-comparado-con-otros-mac": {
            "title": "Nuevo MacBook, el rendimiento de su CPU comparado con otros Mac...",
            "snippet": "Mac Mini a 2,8Ghz, 3064, 6391, 3342, 7064. iMac 21,5 a 1,4Ghz, 2585, 4861, 2804, 5358. iMac 21,5 a 2,9Ghz, 3119, 9660, 3560, 10794. MacBook Pro Retina 13 a 2,7Ghz, 3151, 6548, 3510, 7549. MacBook Pro Retina 15...",
            "date": "2015-04-25",
            "author_name": "Pedro Santamar\u00eda",
            "categories": "macbook,imac",
            "tags": "macbook,macbook_pro,macbook_pro_retina,pro,pro_retina,retina,mini,nuevo,nuevo_macbook,mac,ghz,imac",
            "recuweb_url": "http://es.recuweb.com/imac/applesfera.com/2015/04/nuevo-macbook-el-rendimiento-de-su-cpu-comparado-con-otros-mac",
            "resource_url": "http://www.google.com/search?q=mac%2Bpro&tbm=blg&output=atom&start=0&hl=es&lr=lang_es&nord=1",
            "source_url": "http://applesfera.com/portatil/nuevo-macbook-el-rendimiento-de-su-cpu-en-comparacion-con-otros-mac"
        },
        "javimontero.com/2015/04/instalacion-gpu-msi-r9-280x-en-macpro-2-1-things": {
            "title": "Instalacion GPU MSI R9 280x en MacPro 2,1 - Things...",
            "snippet": "Instalaci\u00f3n de la gr\u00e1fica m\u00e1s potente que admite el Apple MacPro del 2006 para poder editar video en 4K rodado con el Atomos Shogun, Sony A7s y ZenSlider.",
            "date": "2015-04-17",
            "author_name": "Javi",
            "tags": "admite,apple,gpu",
            "recuweb_url": "http://es.recuweb.com/javimontero.com/2015/04/instalacion-gpu-msi-r9-280x-en-macpro-2-1-things",
            "resource_url": "http://www.google.com/search?q=mac%2Bpro%2Bmac%2Bpro&tbm=blg&output=atom&start=0&hl=es&lr=lang_es&nord=1",
            "source_url": "http://javimontero.com/blog/2015/04/instalacion-gpu-msi-r9-280x-en-macpro21/"
        },
        "fansdeapple.com/2015/04/macbook-pro-retina-15-mid-2014-fans-de-apple": {
            "title": "macbook pro retina 15 mid 2014/////- Fans de Apple...",
            "snippet": "Sobre el post del foro T\u00edtulo de la venta: MACBOOK PRO RETINA 15 MID 2014/////\u00bfRelacionado con Apple?: S\u00ed Sobre el producto Marca: APPLE Modelo: MACBOOK PRO RETINA 15\" MID 2014 Precio:...",
            "date": "2015-04-17",
            "author_name": "zorkken",
            "categories": "macbook",
            "tags": "apple,macbook,macbook_pro,macbook_pro_retina,pro,pro_retina,retina,mid",
            "recuweb_url": "http://es.recuweb.com/macbook/fansdeapple.com/2015/04/macbook-pro-retina-15-mid-2014-fans-de-apple",
            "resource_url": "http://www.google.com/search?q=mac%2Bpro&tbm=blg&output=atom&start=0&hl=es&lr=lang_es&nord=1",
            "source_url": "http://fansdeapple.com/showthread.php?p=624977"
        },
        "applesfera.com/2015/04/os-x-amplia-el-soporte-de-pantallas-4k-en-los-mac": {
            "title": "OS X amplia el soporte de pantallas 4K en los Mac...",
            "snippet": "MacBook Pro (Retina, 13-inch, Early 2015); MacBook Pro (Retina, 15-inch, Mid 2014); Mac Pro (Late 2013); iMac (27-inch, Late 2013 and later); Mac mini (Late 2014); MacBook Air (Early 2015); MacBook (Retina, 12-inch,...",
            "date": "2015-04-13",
            "author_name": "Pedro Santamar\u00eda",
            "categories": "macbook,imac",
            "tags": "macbook,macbook_air,air,macbook_pro,pro,soporte,mac,retina,inch,early,mid,late,imac,mini",
            "recuweb_url": "http://es.recuweb.com/imac/applesfera.com/2015/04/os-x-amplia-el-soporte-de-pantallas-4k-en-los-mac",
            "resource_url": "http://www.google.com/search?q=mac%2Bpro%2Bmac%2Bpro&tbm=blg&output=atom&start=0&hl=es&lr=lang_es&nord=1",
            "source_url": "http://applesfera.com/os-x/os-x-10-10-3-amplia-el-soporte-de-pantallas-4k-en-los-mac"
        },
        "faq-mac.com/2015/04/apple-retira-el-soporte-a-los-macbook-pro-de-2009-faq": {
            "title": "Apple retira el soporte a los MacBook Pro de 2009 - Faq-mac...",
            "snippet": "Apple ha actualizado la lista de ordenadores obsoletos para a\u00f1adir todos los MacBook Pro de 2009. Apple hace una peque\u00f1a diferenciaci\u00f3n entre vintage y obsoletos pero es solo una m\u00ednima cuesti\u00f3n legal que solo afecta...",
            "date": "2015-04-10",
            "author_name": "Carlos Burges Ruiz de Gopegui",
            "categories": "macbook",
            "tags": "macbook,macbook_pro,pro,apple,soporte,faq,mac",
            "recuweb_url": "http://es.recuweb.com/macbook/faq-mac.com/2015/04/apple-retira-el-soporte-a-los-macbook-pro-de-2009-faq",
            "resource_url": "http://www.google.com/search?q=mac%2Bpro&tbm=blg&output=atom&start=0&hl=es&lr=lang_es&nord=1",
            "source_url": "http://faq-mac.com/2015/04/apple-retira-el-soporte-a-los-macbook-pro-de-2009/"
        },
        "diario1588.com/2015/04/wholesale-mac-pro-refurb-3iykntm4b9-diario-1588": {
            "title": "wholesale mac pro refurb-3iYkntM4B9 Diario 1588...",
            "snippet": "wholesale mac pro refurb-3iYkntM4B9. Jueves, 09 abril 2015. get their control up from the mobile (unless it all improves an individual's success), and become an individual's body-mind to the office! But if the daily life is not really ensured...",
            "date": "2015-04-09",
            "author_name": "administrador",
            "tags": "mac,pro",
            "recuweb_url": "http://es.recuweb.com/diario1588.com/2015/04/wholesale-mac-pro-refurb-3iykntm4b9-diario-1588",
            "resource_url": "http://www.google.com/search?q=mac%2Bpro%2Bmac%2Bpro&tbm=blg&output=atom&start=0&hl=es&lr=lang_es&nord=1",
            "source_url": "http://diario1588.com/wholesale-mac-pro-refurb-3iykntm4b9/"
        },
        "faq-mac.com/2015/03/otro-uso-para-tu-viejo-mac-pro-caja-discos-duros-faq": {
            "title": "Otro uso para tu viejo Mac Pro: caja para discos duros - Faq-mac...",
            "snippet": "Los Mac Pro disponen de capacidad para almacenar hasta 6 discos duros en las cuatro bah\u00edas dedicadas a ellos adem\u00e1s de la bah\u00eda de la unidad \u00f3ptica, que puede duplicarse utilizando el cable adecuado ya que admite...",
            "date": "2015-03-26",
            "author_name": "Carlos Burges Ruiz de Gopegui",
            "categories": "mac-pro",
            "tags": "puede,admite,adem\u00e1s,mac,mac_pro,pro,uso,faq",
            "recuweb_url": "http://es.recuweb.com/mac-pro/faq-mac.com/2015/03/otro-uso-para-tu-viejo-mac-pro-caja-discos-duros-faq",
            "resource_url": "http://www.google.com/search?q=mac%2Bpro%2Bmac%2Bpro&tbm=blg&output=atom&start=0&hl=es&lr=lang_es&nord=1",
            "source_url": "http://faq-mac.com/2015/03/otro-uso-para-tu-viejo-power-mac/"
        },
        "barefeats.com/2015/03/early-2015-macbook-pro-13-versus-late-2013-15": {
            "title": "'early 2015'MacBook Pro 13\" versus 'late 2013'MacBook Pro 15\"...",
            "snippet": "So which has the best cost/performance ratio, a NEW 'early 2015'Retina MacBook Pro 13\" or a USED 'late 2013'Retina MacBook Pro 15\"? We benchmarked the fastest example of each to answer the question. GRAPH...",
            "date": "2015-03-17",
            "author_name": "desconocido",
            "categories": "macbook",
            "tags": "macbook,macbook_pro,pro,early,late,retina",
            "recuweb_url": "http://es.recuweb.com/macbook/barefeats.com/2015/03/early-2015-macbook-pro-13-versus-late-2013-15",
            "resource_url": "http://www.google.com/search?q=mac%2Bpro&tbm=blg&output=atom&start=0&hl=es&lr=lang_es&nord=1",
            "source_url": "http://barefeats.com/rmbp2015.html"
        },
        "applelizados.com/2015/03/nuevo-macbook-pro-13-pulgadas-retina-applelizados": {
            "title": "Nuevo MacBook Pro 13 pulgadas retina - Applelizados...",
            "snippet": "El nuevo MacBook Pro de 13 pulgadas incorpora pantalla retina y trackpad con tecnolog\u00eda force touch sin botones.",
            "date": "2015-03-09",
            "author_name": "Jose Alfocea",
            "categories": "tecnologia,macbook",
            "tags": "trackpad,force,touch,pantalla,macbook,macbook_pro,pro,nuevo,nuevo_macbook,retina",
            "recuweb_url": "http://es.recuweb.com/macbook/applelizados.com/2015/03/nuevo-macbook-pro-13-pulgadas-retina-applelizados",
            "resource_url": "http://www.google.com/search?q=mac%2Bpro&tbm=blg&output=atom&start=0&hl=es&lr=lang_es&nord=1",
            "source_url": "http://applelizados.com/nuevo-macbook-pro-retina-13-90876"
        }
    }
}