{
    "meta": {
        "portal_name": "formula-uno",
        "language": "es",
        "updated": "20150507"
    },
    "schema": {
        "html:portal": "http://es.recuweb.com/formula-uno/",
        "graph:videos": "http://es.recuweb.com/graph/v1.0/formula-uno/formula-uno/videos.json",
        "graph:news": "http://es.recuweb.com/graph/v1.0/formula-uno/formula-uno/noticias.json",
        "graph:blogs": "http://es.recuweb.com/graph/v1.0/formula-uno/formula-uno/blogs.json"
    },
    "items": {
        "f1aldia.com/2015/05/timo-glock-las-carreras-de-f%C3%B3rmula-1-se-han-vuelto-muy": {
            "title": "Timo Glock: \"Las carreras de F\u00f3rmula 1 se han vuelto muy aburridas...",
            "snippet": "Las carreras de F\u00f3rmula 1 se han vuelto muy aburridas, no es como con nosotros (en el DTM). Con la excepci\u00f3n del Ferrari de Sebastian Vettel, nadie es capaz de seguir el ritmo de los de delante\", explic\u00f3 Timo Glock en...",
            "date": "2015-05-01",
            "author_name": "desconocido",
            "tags": "sebastian,sebastian_vettel,vettel,excepci\u00f3n,carreras,f\u00f3rmula,muy,ferrari,explic\u00f3",
            "recuweb_url": "http://es.recuweb.com/f1aldia.com/2015/05/timo-glock-las-carreras-de-f%C3%B3rmula-1-se-han-vuelto-muy",
            "resource_url": "http://www.google.com/search?q=formula%2Buno&tbm=blg&output=atom&start=0&hl=es&lr=lang_es&nord=1",
            "source_url": "http://f1aldia.com/26372/timo-glock-carreras-formula-1-vuelto-muy-aburridas/"
        },
        "gpupdate.net/2015/04/la-temporada-2016-de-f%C3%B3rmula-1-arrancar%C3%A1-en-abril": {
            "title": "La temporada 2016 de F\u00f3rmula 1 arrancar\u00e1 en abril -...",
            "snippet": "29 de abril de 2015 La F\u00f3rmula 1 comenzar\u00e1 dos semanas m\u00e1s tarde de lo habitual la pr\u00f3xima temporada de 2016 despu\u00e9s que los organizadores del Gran Premio de Australia hayan anunciado que la carrera de Melbourne se llevar\u00e1 a...",
            "date": "2015-04-29",
            "author_name": "desconocido",
            "tags": "gran,gran_premio,premio,temporada,f\u00f3rmula,dos,carrera",
            "recuweb_url": "http://es.recuweb.com/gpupdate.net/2015/04/la-temporada-2016-de-f%C3%B3rmula-1-arrancar%C3%A1-en-abril",
            "resource_url": "http://www.google.com/search?q=formula%2Buno&tbm=blg&output=atom&start=0&hl=es&lr=lang_es&nord=1",
            "source_url": "http://gpupdate.net/es/noticias-f1/324929/la-temporada-2016-de-formula-1-arrancara-en-abril/"
        },
        "sportyou.es/2015/04/roberto-merhi-confiesa-su-cruda-realidad-en-la-f%C3%B3rmula-1-sportyou": {
            "title": "Roberto Merhi confiesa su cruda realidad en la F\u00f3rmula 1 - Sportyou...",
            "snippet": "Roberto Merhi s\u00f3lo tiene asegurado su futuro en F\u00f3rmula 1 para el GP de Espa\u00f1a, y despu\u00e9s no lo tiene nada claro.",
            "date": "2015-04-27",
            "author_name": "David S\u00e1nchez de Castro",
            "tags": "tiene,nada,futuro,f\u00f3rmula,espa\u00f1a",
            "recuweb_url": "http://es.recuweb.com/sportyou.es/2015/04/roberto-merhi-confiesa-su-cruda-realidad-en-la-f%C3%B3rmula-1-sportyou",
            "resource_url": "http://www.google.com/search?q=formula%2Buno&tbm=blg&output=atom&start=0&hl=es&lr=lang_es&nord=1",
            "source_url": "http://sportyou.es/blog/formula-1/2015/04/27/roberto-merhi-futuro-f1-535068.html"
        },
        "omicrono.com/2015/04/tecnolog%C3%ADa-de-formula-1-para-las-neveras-omicrono": {
            "title": "Tecnolog\u00eda de Formula 1 para las neveras - Omicrono...",
            "snippet": "La tecnolog\u00eda de Formula 1 que emplea el equipo Williams ser\u00e1 utilizada en las neveras de los supermercados. El consumo de energ\u00eda de los frigor\u00edficos supone un alto porcentaje del coste total en un supermercado.",
            "date": "2015-04-26",
            "author_name": "Ignacio Losada Perez",
            "categories": "tecnologia",
            "tags": "coste,equipo,tecnolog\u00eda,formula,williams",
            "recuweb_url": "http://es.recuweb.com/tecnologia/omicrono.com/2015/04/tecnolog%C3%ADa-de-formula-1-para-las-neveras-omicrono",
            "resource_url": "http://www.google.com/search?q=formula%2Buno&tbm=blg&output=atom&start=0&hl=es&lr=lang_es&nord=1",
            "source_url": "http://omicrono.com/2015/04/tecnologia-f1-de-williams-usada-en-frigorificos/"
        },
        "radioestar.wordpress.com/2015/04/la-f%C3%B3rmula-repetir": {
            "title": "\u00bfLA F\u00d3RMULA?...REPETIR LA F\u00d3RMULA...",
            "snippet": "Vi\u00f1eta de Salvatore Si no quieres una taza, dos. Si no quieres una pinza, dos. As\u00ed es y as\u00ed nos lo est\u00e1n contando. El sistema, s\u00ed, el sistema, ese del que...",
            "date": "2015-04-22",
            "author_name": "CANAL AGRIPA",
            "tags": "f\u00f3rmula,dos",
            "recuweb_url": "http://es.recuweb.com/radioestar.wordpress.com/2015/04/la-f%C3%B3rmula-repetir",
            "resource_url": "http://es.search.wordpress.com/?q=formula%2Buno&f=feed&page=1",
            "source_url": "http://radioestar.wordpress.com/2015/04/22/la-formula-repetir-la-formula/"
        },
        "deportes.starmedia.com/2015/04/resultados-del-gran-premio-de-china-f%C3%B3rmula-uno-2015-starmedia": {
            "title": "Resultados del Gran Premio de China F\u00f3rmula Uno 2015 starMedia...",
            "snippet": "Ent\u00e9rate de el resultado completo del Gran Premio de China de la F\u00f3rmula Uno. Aqu\u00ed encontraras el listado completo.",
            "date": "2015-04-12",
            "author_name": "desconocido",
            "tags": "china,f\u00f3rmula,gran,gran_premio,premio",
            "recuweb_url": "http://es.recuweb.com/deportes.starmedia.com/2015/04/resultados-del-gran-premio-de-china-f%C3%B3rmula-uno-2015-starmedia",
            "resource_url": "http://www.google.com/search?q=formula%2Buno&tbm=blg&output=atom&start=0&hl=es&lr=lang_es&nord=1",
            "source_url": "http://deportes.starmedia.com/motor/resultados-gran-premio-china-formula-uno-2015.html"
        },
        "informador.com.mx/2015/04/china-tercera-parada-de-la-f%C3%B3rmula-1-el-informador": {
            "title": "China, tercera parada de la F\u00f3rmula 1:: El Informador...",
            "snippet": "GUADALAJARA, JALISCO (09/ABR/2015).- En una F\u00f3rmula Uno necesitada de competencias m\u00e1s cerradas y nuevas rivalidades, el triunfo de Sebastian Vettel y Ferrari en Malasia fue una aut\u00e9ntica bocanada de aire fresco para la m\u00e1xima...",
            "date": "2015-04-09",
            "author_name": "desconocido",
            "tags": "sebastian,sebastian_vettel,vettel,china,f\u00f3rmula,informador,guadalajara,jalisco,ferrari",
            "recuweb_url": "http://es.recuweb.com/informador.com.mx/2015/04/china-tercera-parada-de-la-f%C3%B3rmula-1-el-informador",
            "resource_url": "http://www.google.com/search?q=formula%2Buno&tbm=blg&output=atom&start=0&hl=es&lr=lang_es&nord=1",
            "source_url": "http://informador.com.mx/deportes/2015/585644/6/china-tercera-para-de-la-formula-1.htm"
        },
        "jorgedelacruz.es/2015/04/el-blog-de-jorge-la-cruz-zimbra-a%C3%B1adiendo-un-servidor-slave": {
            "title": "El Blog de Jorge de la Cruz Zimbra: A\u00f1adiendo un servidor Slave...",
            "snippet": "rootzcs2 yum -y install bind rootzcs2 vim/etc/options listen-on port 53;.; allow-query localhost;.0/24;; forwarders;.!;;. zone \" \" IN type slave; file \" \"; masters.... Como seria la mejor formula de calculo para ello o mejor realizarlo todo en un...",
            "date": "2015-04-07",
            "author_name": "Jorge de la Cruz",
            "tags": "ello,formula",
            "recuweb_url": "http://es.recuweb.com/jorgedelacruz.es/2015/04/el-blog-de-jorge-la-cruz-zimbra-a%C3%B1adiendo-un-servidor-slave",
            "resource_url": "http://www.google.com/search?q=es%2Blocalhost%2Bcom%2Bformula%2Buno&tbm=blg&output=atom&start=0&hl=es&lr=lang_es&nord=1",
            "source_url": "http://jorgedelacruz.es/2015/04/07/zimbra-anadiendo-un-servidor-slave-de-ldap-y-dns/"
        },
        "f1aldia.com/2015/04/max-mosley-si-todo-contin%C3%BAa-as%C3%AD-la-f%C3%B3rmula-1-se-derrumbar%C3%A1": {
            "title": "Max Mosley: \"Si todo contin\u00faa as\u00ed, la F\u00f3rmula 1 se derrumbar\u00e1\" - F1...",
            "snippet": "En nuestra primera temporada con el equipo March en la F\u00f3rmula 1 ten\u00edamos un presupuesto de libras, lo que ser\u00eda hoy -ajustado a la inflaci\u00f3n- entre uno y dos millones. Pero hoy se necesita cien veces esa...",
            "date": "2015-04-07",
            "author_name": "desconocido",
            "tags": "primera,temporada,equipo,f\u00f3rmula,ser\u00eda,dos",
            "recuweb_url": "http://es.recuweb.com/f1aldia.com/2015/04/max-mosley-si-todo-contin%C3%BAa-as%C3%AD-la-f%C3%B3rmula-1-se-derrumbar%C3%A1",
            "resource_url": "http://www.google.com/search?q=formula%2Buno&tbm=blg&output=atom&start=0&hl=es&lr=lang_es&nord=1",
            "source_url": "http://f1aldia.com/26138/max-mosley-si-todo-continua-asi-formula-1-derrumbara/"
        },
        "informador.com.mx/2015/03/termina-la-espera-en-f%C3%B3rmula-1-el-informador": {
            "title": "Termina la espera en la F\u00f3rmula 1:: El Informador...",
            "snippet": "GUADALAJARA, JALISCO (12/MAR/2015).- El eterno receso invernal, tal como ven los aficionados de la F\u00f3rmula Uno a la transici\u00f3n entre el fin de una temporada y el inicio de una nueva, termina este fin de semana, con la puesta en marcha...",
            "date": "2015-03-12",
            "author_name": "desconocido",
            "tags": "semana,temporada,f\u00f3rmula,informador,guadalajara,jalisco,fin",
            "recuweb_url": "http://es.recuweb.com/informador.com.mx/2015/03/termina-la-espera-en-f%C3%B3rmula-1-el-informador",
            "resource_url": "http://www.google.com/search?q=formula%2Buno&tbm=blg&output=atom&start=0&hl=es&lr=lang_es&nord=1",
            "source_url": "http://informador.com.mx/deportes/2015/580960/6/termina-la-espera-en-la-formula-1.htm"
        }
    }
}