{
    "meta": {
        "portal_name": "juegos-ol\u00edmpicos",
        "language": "es",
        "updated": "20150507"
    },
    "schema": {
        "html:portal": "http://es.recuweb.com/juegos-ol\u00edmpicos/",
        "graph:videos": "http://es.recuweb.com/graph/v1.0/juegos-ol%C3%ADmpicos/juegos-ol%C3%ADmpicos/videos.json",
        "graph:news": "http://es.recuweb.com/graph/v1.0/juegos-ol%C3%ADmpicos/juegos-ol%C3%ADmpicos/noticias.json",
        "graph:blogs": "http://es.recuweb.com/graph/v1.0/juegos-ol%C3%ADmpicos/juegos-ol%C3%ADmpicos/blogs.json"
    },
    "items": {
        "elpais.cr/2015/05/arena-corinthians-acoger%C3%A1-partidos-de-los-juegos-ol%C3%ADmpicos-2016": {
            "title": "Arena Corinthians acoger\u00e1 partidos de los Juegos Ol\u00edmpicos 2016...",
            "snippet": "R\u00edo de Janeiro, 1 may (EFE).- Un acuerdo anunciado el pasado jueves permitir\u00e1 que la Arena Corinthians, el estadio construido en la ciudad brasile\u00f1a de Sao Paulo para el Mundial Brasil 2014, albergue diez de los partidos...",
            "date": "2015-05-01",
            "author_name": "Cristian \u00c1lvarez",
            "tags": "mundial,brasil,estadio,jueves,juegos,juegos_ol\u00edmpicos,ol\u00edmpicos,r\u00edo,janeiro,ciudad,brasile\u00f1a",
            "recuweb_url": "http://es.recuweb.com/elpais.cr/2015/05/arena-corinthians-acoger%C3%A1-partidos-de-los-juegos-ol%C3%ADmpicos-2016",
            "resource_url": "http://www.google.com/search?q=juegos%2Bol%C3%ADmpicos&tbm=blg&output=atom&start=0&hl=es&lr=lang_es&nord=1",
            "source_url": "http://elpais.cr/2015/05/01/arena-corinthians-acogera-partidos-de-los-olimpicos-del-2016/"
        },
        "basketfem.com/2015/05/estados-unidos-comienza-su-preparaci%C3%B3n-para-los-juegos": {
            "title": "Estados Unidos comienza su preparaci\u00f3n para los Juegos...",
            "snippet": "La selecci\u00f3n de Estados Unidos comienza la preparaci\u00f3n para R\u00edo 2016 con un stage de 2 d\u00edas Seguir a elecapo87 Seguir a Basketfem Las recientes Campeonas del Mundo y de los Juegos Ol\u00edmpicos van a comenzar...",
            "date": "2015-05-01",
            "author_name": "elecapo87",
            "tags": "ol\u00edmpicos,juegos,selecci\u00f3n,r\u00edo,d\u00edas,mundo",
            "recuweb_url": "http://es.recuweb.com/basketfem.com/2015/05/estados-unidos-comienza-su-preparaci%C3%B3n-para-los-juegos",
            "resource_url": "http://www.google.com/search?q=juegos%2Bol%C3%ADmpicos&tbm=blg&output=atom&start=0&hl=es&lr=lang_es&nord=1",
            "source_url": "http://basketfem.com/2015/05/01/estados-unidos-comienza-su-preparacion-para-los-juegos-olimpicos-de-2016/"
        },
        "laplazacycles.com/2015/04/ciclismo-en-los-juegos-olimpicos-rio-2016-laplaza-cycles": {
            "title": "CICLISMO EN LOS JUEGOS OLIMPICOS RIO 2016 - LaPlaza Cycles...",
            "snippet": "El ciclismo en los Juegos Ol\u00edmpicos de R\u00edo de Janeiro 2016 se realizar\u00e1 en diversas sedes de la ciudad de Rio de Janeiro del 6 al 20 de agosto de 2016. Se disputaran 18 pruebas diferentes, 9 masculinas y 9 femeninas,...",
            "date": "2015-04-29",
            "author_name": "admin",
            "tags": "realizar\u00e1,juegos,juegos_ol\u00edmpicos,ol\u00edmpicos,r\u00edo,janeiro,ciudad",
            "recuweb_url": "http://es.recuweb.com/laplazacycles.com/2015/04/ciclismo-en-los-juegos-olimpicos-rio-2016-laplaza-cycles",
            "resource_url": "http://www.google.com/search?q=juegos%2Bol%C3%ADmpicos&tbm=blg&output=atom&start=0&hl=es&lr=lang_es&nord=1",
            "source_url": "http://laplazacycles.com/ciclismo-en-los-juegos-olimpicos-rio-2016/"
        },
        "surf30.net/2015/04/surf-en-los-juegos-ol%C3%ADmpicos-de-tokio-30": {
            "title": "\u00bfSurf en los Juegos Ol\u00edmpicos de Tokio? Surf 30...",
            "snippet": "El sue\u00f1o del presidente de la International Surfing Association, Fernando Aguerre, siempre ha sido que el surf estuviera presente en los juegos ol\u00edmpicos. Las particularidades de este deporte para su pr\u00e1ctica en competici\u00f3n...",
            "date": "2015-04-29",
            "author_name": "Surf Treinta",
            "categories": "surf,deporte",
            "tags": "juegos,juegos_ol\u00edmpicos,ol\u00edmpicos,tokio,presidente,deporte",
            "recuweb_url": "http://es.recuweb.com/deporte/surf30.net/2015/04/surf-en-los-juegos-ol%C3%ADmpicos-de-tokio-30",
            "resource_url": "http://www.google.com/search?q=juegos%2Bol%C3%ADmpicos&tbm=blg&output=atom&start=0&hl=es&lr=lang_es&nord=1",
            "source_url": "http://surf30.net/2015/04/surf-en-los-juegos-olimpicos-de-tokio.html"
        },
        "blogs.20minutos.es/2015/04/la-curiosa-primera-final-de-100-metros-lisos-en-los-juegos": {
            "title": "La curiosa primera final de 100 metros lisos en los Juegos... - Blogs...",
            "snippet": "Gracias al empe\u00f1o y trabajo del bar\u00f3n Pierre de Coubertin se celebr\u00f3 en Atenas (del 6 al 15 de abril de 1896) los primeros Juegos Ol\u00edmpicos de la Era Moderna. El d\u00eda 10 de abril se disput\u00f3 en el Estadio Panathinaik\u00f3 la final...",
            "date": "2015-04-28",
            "author_name": "Alfred L\u00f3pez",
            "tags": "estadio,era,ol\u00edmpicos,primera,juegos,gracias",
            "recuweb_url": "http://es.recuweb.com/blogs.20minutos.es/2015/04/la-curiosa-primera-final-de-100-metros-lisos-en-los-juegos",
            "resource_url": "http://www.google.com/search?q=juegos%2Bol%C3%ADmpicos&tbm=blg&output=atom&start=0&hl=es&lr=lang_es&nord=1",
            "source_url": "http://blogs.20minutos.es/yaestaellistoquetodolosabe/la-curiosa-primera-final-de-100-metros-lisos-en-los-juegos-olimpicos-de-1896/"
        },
        "metro.pr/2015/04/nada-de-peloteros-grandes-ligas-en-juegos-ol%C3%ADmpicos-metro": {
            "title": "Nada de peloteros de Grandes Ligas en Juegos Ol\u00edmpicos Metro...",
            "snippet": "NUEVA YORK (AP) No esperen ver a jugadores de Grandes Ligas en los Juegos Ol\u00edmpicos de 2020, si es que el COI vuelve a incluir al b\u00e9isbol en el programa de esa justa en Tokio.",
            "date": "2015-04-24",
            "author_name": "desconocido",
            "categories": "beisbol",
            "tags": "incluir,justa,juegos,juegos_ol\u00edmpicos,ol\u00edmpicos,nueva,grandes,tokio",
            "recuweb_url": "http://es.recuweb.com/beisbol/metro.pr/2015/04/nada-de-peloteros-grandes-ligas-en-juegos-ol%C3%ADmpicos-metro",
            "resource_url": "http://www.google.com/search?q=juegos%2Bol%C3%ADmpicos&tbm=blg&output=atom&start=0&hl=es&lr=lang_es&nord=1",
            "source_url": "http://metro.pr/metrosport/nada-de-peloteros-de-grandes-ligas-en-juegos-olimpicos/pGXodx!mFDsYoo1TGzEA/"
        },
        "cahuracan.com/2015/04/taekwondo-juegos-ol%C3%ADmpicos-de-la-juventud-2018-c-a-hurac%C3%A1n": {
            "title": "Taekwondo. Juegos Ol\u00edmpicos de la Juventud 2018 C. A. Hurac\u00e1n...",
            "snippet": "Los cadetes Leandro Ibarrola y Santiago Ben\u00edtez del equipo de Taekwondo Hurac\u00e1n se encuentran prepar\u00e1ndose en los centros de crecimiento del Enard pensando en los Juegos Ol\u00edmpicos de la Juventud 2018 que se...",
            "date": "2015-04-23",
            "author_name": "prensa",
            "categories": "taekwondo",
            "tags": "juegos,juegos_ol\u00edmpicos,ol\u00edmpicos,taekwondo,juventud,enard",
            "recuweb_url": "http://es.recuweb.com/taekwondo/cahuracan.com/2015/04/taekwondo-juegos-ol%C3%ADmpicos-de-la-juventud-2018-c-a-hurac%C3%A1n",
            "resource_url": "http://www.google.com/search?q=juegos%2Bol%C3%ADmpicos&tbm=blg&output=atom&start=0&hl=es&lr=lang_es&nord=1",
            "source_url": "http://cahuracan.com/2015/04/23/taekwondoistas-del-club-con-vista-a-los-juegos-olimpicos-de-la-juventud-2018/"
        },
        "infomundokayak.wordpress.com/2015/04/canotaje-marcelo-barra-se-carga-al-hombro-los-juegos-ol%C3%ADmpicos": {
            "title": "canotaje: marcelo barra se carga al hombro los juegos ol\u00edmpicos de...",
            "snippet": "El domingo el canotaje tuvo una excelente noticia a trav\u00e9s de la escuela n\u00e1utico La Ribera, donde se lanz\u00f3 oficialmente las actividades del Centro de Desarrollo Ol\u00edmpico de Canotaje del ENARD, de cara a los Juegos...",
            "date": "2015-04-17",
            "author_name": "Mundo Kayak",
            "categories": "escuela",
            "tags": "cara,ol\u00edmpicos,oficialmente,juegos,enard",
            "recuweb_url": "http://es.recuweb.com/escuela/infomundokayak.wordpress.com/2015/04/canotaje-marcelo-barra-se-carga-al-hombro-los-juegos-ol%C3%ADmpicos",
            "resource_url": "http://www.google.com/search?q=juegos%2Bol%C3%ADmpicos&tbm=blg&output=atom&start=0&hl=es&lr=lang_es&nord=1",
            "source_url": "http://infomundokayak.wordpress.com/2015/04/17/canotaje-marcelo-barra-se-carga-al-hombro-los-juegos-olimpicos-de-la-juventud-2018/"
        },
        "noqueando.com/2015/04/anderson-silva-quiere-competir-en-los-juegos-ol%C3%ADmpicos-de-2016-rio": {
            "title": "Anderson Silva quiere competir en los Juegos Ol\u00edmpicos de 2016 en Rio...",
            "snippet": "El ex campe\u00f3n de UFC, Anderson Silva ha solicitado formalmente a la Federaci\u00f3n Brasile\u00f1a de Taekwondo que se le permita competir en el pr\u00f3ximo a\u00f1o Juegos Ol\u00edmpicos...",
            "date": "2015-04-14",
            "author_name": "varelas2s",
            "categories": "taekwondo",
            "tags": "brasile\u00f1a,juegos,juegos_ol\u00edmpicos,ol\u00edmpicos,rio,taekwondo,pr\u00f3ximo",
            "recuweb_url": "http://es.recuweb.com/taekwondo/noqueando.com/2015/04/anderson-silva-quiere-competir-en-los-juegos-ol%C3%ADmpicos-de-2016-rio",
            "resource_url": "http://es.search.wordpress.com/?q=juegos%2Bol%C3%ADmpicos&f=feed&page=1",
            "source_url": "http://noqueando.com/2015/04/14/anderson-silva-quiere-competir-en-los-juegos-olimpicos-de-2016-en-rio/"
        },
        "puntogeek.com/2014/12/los-videojuegos-deber%C3%ADan-estar-en-juegos-ol%C3%ADmpicos": {
            "title": "\"Los videojuegos deber\u00edan estar en los Juegos Ol\u00edmpicos\"...",
            "snippet": "Los videojuegos deber\u00edan estar en los Juegos Ol\u00edmpicos, seg\u00fan le dijo el creador de World of Warcraft a la famosa cadena BBC. Rob Pardo, quien hasta julio era el director creativo de Blizzard Entertainment, dijo que...",
            "date": "2014-12-26",
            "author_name": "Federico Manuel Ayala",
            "categories": "videojuego",
            "tags": "era,juegos,juegos-ol\u00edmpicos,ol\u00edmpicos,estar",
            "recuweb_url": "http://es.recuweb.com/videojuego/puntogeek.com/2014/12/los-videojuegos-deber%C3%ADan-estar-en-juegos-ol%C3%ADmpicos",
            "resource_url": "http://www.google.com/search?q=es%2Blocalhost%2Bcom%2Bjuegos%2Bol%C3%ADmpicos&tbm=blg&output=atom&start=0&hl=es&lr=lang_es&nord=1",
            "source_url": "http://puntogeek.com/2014/12/26/los-videojuegos-deberian-estar-en-los-juegos-olimpicos/"
        }
    }
}