{
    "meta": {
        "portal_name": "billar",
        "language": "es"
    },
    "schema": {
        "html:portal": "http://es.recuweb.com/billar/",
        "graph:videos": "http://es.recuweb.com/graph/v1.0/billar/billar/videos.json",
        "graph:news": "http://es.recuweb.com/graph/v1.0/billar/billar/noticias.json",
        "graph:blogs": "http://es.recuweb.com/graph/v1.0/billar/billar/blogs.json"
    },
    "translations": {
        "es": {
            "term_title": "Billar",
            "term_title_slug": "billar"
        },
        "en": {
            "term_title": "Cue sports",
            "term_title_slug": "cue-sports"
        },
        "fr": {
            "term_title": "Billard",
            "term_title_slug": "billard"
        }
    }
}