{
    "meta": {
        "portal_name": "surf",
        "language": "es",
        "updated": "20150427"
    },
    "schema": {
        "html:portal": "http://es.recuweb.com/surf/",
        "graph:videos": "http://es.recuweb.com/graph/v1.0/surf/surf/videos.json",
        "graph:news": "http://es.recuweb.com/graph/v1.0/surf/surf/noticias.json",
        "graph:blogs": "http://es.recuweb.com/graph/v1.0/surf/surf/blogs.json"
    },
    "items": {
        "surf30.net/2015/04/casi-plato-surf-30": {
            "title": "Casi plato Surf 30...",
            "snippet": "Un d\u00eda sin viento, el mar como un espejo, pero casi ni una ola. Si ten\u00edas paciencia, muy de vez en cuando llegaba una serie de una o dos olas de medio metro solo apta para tablones o paddles.",
            "date": "2015-04-23",
            "author_name": "Surf Treinta",
            "categories": "surf",
            "tags": "serie,dos,olas,mar,d\u00eda,viento,surf,muy",
            "recuweb_url": "http://es.recuweb.com/surf/surf30.net/2015/04/casi-plato-surf-30",
            "resource_url": "http://www.google.com/search?q=surf&tbm=blg&output=atom&start=0&hl=es&lr=lang_es&nord=1",
            "source_url": "http://surf30.net/2015/04/casi-plato.html"
        },
        "surf30.net/2015/04/cazado-en-mavericks-surf-30": {
            "title": "Cazado en Mavericks Surf 30...",
            "snippet": "C\u00f3mo es ser cazado por una serie en Mavericks? Mark Healey nos lo explica en primera persona. Ver la serie llegar, remar con fuerza, comprobar que no lo vas a conseguir, prepararte, saltar, bucear, rezar.",
            "date": "2015-04-23",
            "author_name": "Surf Treinta",
            "categories": "surf",
            "tags": "serie,primera,surf,rezar",
            "recuweb_url": "http://es.recuweb.com/surf/surf30.net/2015/04/cazado-en-mavericks-surf-30",
            "resource_url": "http://www.google.com/search?q=surf&tbm=blg&output=atom&start=0&hl=es&lr=lang_es&nord=1",
            "source_url": "http://surf30.net/2015/04/cazado-en-mavericks.html"
        },
        "surf30.net/2015/04/ma%C3%B1ana-sabremos-el-ganador-del-margaret-river-pro-surf-30": {
            "title": "Ma\u00f1ana sabremos el ganador del Margaret River Pro Surf 30...",
            "snippet": "La organizaci\u00f3n del Drug Aware Margaret River Pro se ha visto obligada a aplazar un d\u00eda m\u00e1s la celebraci\u00f3n de las semifinales y la final de la modalidad masculina. Pese a que el tama\u00f1o era el adecuado, el fuerte viento del...",
            "date": "2015-04-23",
            "author_name": "Surf Treinta",
            "categories": "surf",
            "tags": "viento,era,visto,d\u00eda,pro,surf",
            "recuweb_url": "http://es.recuweb.com/surf/surf30.net/2015/04/ma%C3%B1ana-sabremos-el-ganador-del-margaret-river-pro-surf-30",
            "resource_url": "http://www.google.com/search?q=surf&tbm=blg&output=atom&start=0&hl=es&lr=lang_es&nord=1",
            "source_url": "http://surf30.net/2015/04/manana-sabremos-el-ganador-del-margaret.html"
        },
        "surf30.net/2015/04/qu%C3%A9-fu%C3%A9-de-la-vieja-playa-gros-surf-30": {
            "title": "\u00bfQu\u00e9 fu\u00e9 de la vieja playa de Gros? Surf 30...",
            "snippet": "Interesant\u00edsimo art\u00edculo de Mikel Huarte basado en la entrevista realizada a Juanpe Sansinenea, un veterano del surf, y a Alain Gonfaus, escritor y autor del libro \"Surfers\" (2006), en el que describen los inicios del surf en la...",
            "date": "2015-04-23",
            "author_name": "Surf Treinta",
            "categories": "surf",
            "tags": "playa,surf",
            "recuweb_url": "http://es.recuweb.com/surf/surf30.net/2015/04/qu%C3%A9-fu%C3%A9-de-la-vieja-playa-gros-surf-30",
            "resource_url": "http://www.google.com/search?q=surf%2Bsurf&tbm=blg&output=atom&start=0&hl=es&lr=lang_es&nord=1",
            "source_url": "http://surf30.net/2015/04/que-fue-de-la-vieja-playa-de-gros.html"
        },
        "surf30.net/2015/04/dos-islas-surf-30": {
            "title": "Dos islas Surf 30...",
            "snippet": "Nic Von Rupp se pas\u00f3 en Hawai buena parte del invierno. Despu\u00e9s de surfear mucho en el North Shore de Oahu, con Pipe bombeando continuamente, el portugu\u00e9s se fue a Maui, donde se encontr\u00f3 con Matt Meola y Albee...",
            "date": "2015-04-22",
            "author_name": "Surf Treinta",
            "categories": "surf",
            "tags": "buena,dos,surf,hawai,oahu",
            "recuweb_url": "http://es.recuweb.com/surf/surf30.net/2015/04/dos-islas-surf-30",
            "resource_url": "http://www.google.com/search?q=surf%2Bsurf&tbm=blg&output=atom&start=0&hl=es&lr=lang_es&nord=1",
            "source_url": "http://surf30.net/2015/04/dos-islas.html"
        },
        "revistaoxigeno.es/2015/04/madrid-lisboa-en-paddle-surf-revista-oxigeno": {
            "title": "Madrid-Lisboa en paddle surf Revista Oxigeno...",
            "snippet": "El pr\u00f3ximo viernes d\u00eda 24 de abril a las 15:30 horas en la feria Surf Expo Spain en el Palacio de Vistalegre (Calle de Utebo, 1, 28025 Madrid) el aventurero desvelar\u00e1 todos los detalles. En el acto, el Embajador de Turismo...",
            "date": "2015-04-21",
            "author_name": "Jorge Jimenez",
            "categories": "surf",
            "tags": "surf,abril,pr\u00f3ximo,d\u00eda",
            "recuweb_url": "http://es.recuweb.com/surf/revistaoxigeno.es/2015/04/madrid-lisboa-en-paddle-surf-revista-oxigeno",
            "resource_url": "http://www.google.com/search?q=surf&tbm=blg&output=atom&start=0&hl=es&lr=lang_es&nord=1",
            "source_url": "http://revistaoxigeno.es/madrid-lisboa-en-paddle-surf/"
        },
        "surf30.net/2015/04/el-surf-herido-de-muerte-en-isla-reuni%C3%B3n-30": {
            "title": "El surf, herido de muerte en Isla Reuni\u00f3n Surf 30...",
            "snippet": "Hasta hace no mucho Isla Reuni\u00f3n era destino para muchos surfistas, cantera de campeones de Francia, pero los ataques de tiburones han hecho que muchos surfistas se hayan visto obligados a abandonar la isla para...",
            "date": "2015-04-20",
            "author_name": "Surf Treinta",
            "categories": "surf",
            "tags": "surfistas,visto,isla,era,surf,muerte",
            "recuweb_url": "http://es.recuweb.com/surf/surf30.net/2015/04/el-surf-herido-de-muerte-en-isla-reuni%C3%B3n-30",
            "resource_url": "http://www.google.com/search?q=surf%2Bsurf&tbm=blg&output=atom&start=0&hl=es&lr=lang_es&nord=1",
            "source_url": "http://surf30.net/2015/04/el-surf-herido-de-muerte-en-isla-reunion.html"
        },
        "blogs.comunitatvalenciana.com/2015/04/llega-el-surf-al-loco-club-con-grupo-smilesurf": {
            "title": "Llega el surf al Loco Club con el grupo SMILESurf Surf...",
            "snippet": "Llega el surf al Loco Club con el grupo SMILE. 10682309_947590228619164_844889803187947468_o. Este s\u00e1bado 18 noche ya tenemos plan para disfrutar de buena m\u00fasica en directo con el grupo SMILE en el Loco...",
            "date": "2015-04-16",
            "author_name": "Pepo Torres",
            "categories": "surf",
            "tags": "disfrutar,buena,surf",
            "recuweb_url": "http://es.recuweb.com/surf/blogs.comunitatvalenciana.com/2015/04/llega-el-surf-al-loco-club-con-grupo-smilesurf",
            "resource_url": "http://www.google.com/search?q=surf%2Bsurf&tbm=blg&output=atom&start=0&hl=es&lr=lang_es&nord=1",
            "source_url": "http://blogs.comunitatvalenciana.com/surf/2015/04/17/llega-el-surf-al-loco-club-con-el-grupo-smile/"
        },
        "pijamasurf.com/2015/04/el-ano-masculino-y-placer-del-pegging-son-m%C3%A1ximo-tab%C3%BA": {
            "title": "\u00bfEl ano masculino (y el placer del 'pegging') son el m\u00e1ximo tab\u00fa...",
            "snippet": "... Arte audiovisual Arte contempor\u00e1neo Arte sagrado Arte Urbano Biblioteca Pijamasurf Cine Fotograf\u00eda Gr\u00e1fica Literatura Plastica Soniricall Web Art Deportes Deportes extremos Futbol M\u00e1s deportes Surf...",
            "date": "2015-04-16",
            "author_name": "pijamasurf",
            "categories": "cine,fotografia,literatura,placer,futbol,surf",
            "tags": "surf",
            "recuweb_url": "http://es.recuweb.com/surf/pijamasurf.com/2015/04/el-ano-masculino-y-placer-del-pegging-son-m%C3%A1ximo-tab%C3%BA",
            "resource_url": "http://www.google.com/search?q=surf%2Bsurf&tbm=blg&output=atom&start=0&hl=es&lr=lang_es&nord=1",
            "source_url": "http://pijamasurf.com/2015/04/el-ano-masculino-y-el-placer-del-pegging-son-el-maximo-tabu-heterosexual/"
        },
        "pijamasurf.com/2015/04/te-atraen-los-hombres-de-barba-y-tatuajes-hay-una-raz%C3%B3n": {
            "title": "\u00bfTe atraen los hombres de barba y tatuajes? Hay una raz\u00f3n...",
            "snippet": "Incluso el cerebro humano, con toda su complejidad, podr\u00eda ser equivalente a la cola iridiscente del pavo real. Tambi\u00e9n en Pijama Surf: Ilusiones \u00f3pticas en la piel: impresionantes tatuajes 3D que creer\u00edas imposibles.",
            "date": "2015-04-05",
            "author_name": "pijamasurf",
            "categories": "surf",
            "tags": "surf,hay",
            "recuweb_url": "http://es.recuweb.com/surf/pijamasurf.com/2015/04/te-atraen-los-hombres-de-barba-y-tatuajes-hay-una-raz%C3%B3n",
            "resource_url": "http://www.google.com/search?q=surf%2Bsurf&tbm=blg&output=atom&start=0&hl=es&lr=lang_es&nord=1",
            "source_url": "http://pijamasurf.com/2015/04/te-atraen-los-hombres-de-barba-y-tatuajes-hay-una-razon-cientifica-para-ello/"
        }
    }
}